epay_nepal/__init__.py
epay_nepal/asgi.py
epay_nepal/settings.py
epay_nepal/urls.py
epay_nepal/wsgi.py
epay_nepal-0.1.0.dist-info/METADATA
epay_nepal-0.1.0.dist-info/WHEEL
epay_nepal-0.1.0.dist-info/RECORD
